index_by/__init__.py
index_by/attr.py
index_by/key.py
index_by/modifier.py
index_by/pop_key.py
index_by/modifiers/__init__.py
index_by/modifiers/attr.py
index_by/modifiers/key.py
index_by/modifiers/pop_key.py
index_by-0.1.0.dist-info/LICENSE
index_by-0.1.0.dist-info/METADATA
index_by-0.1.0.dist-info/WHEEL
index_by-0.1.0.dist-info/top_level.txt
index_by-0.1.0.dist-info/RECORD
