Metadata-Version: 2.1
Name: index-by
Version: 0.1.0
Summary: Index objects in a sequence easily
Home-page: https://github.com/twiebe/py-index-by
Author: Thomas Wiebe
Author-email: code@heimblick.net
License: BSD
Platform: any
Classifier: Intended Audience :: Developers
Classifier: License :: OSI Approved :: BSD License
Classifier: Operating System :: OS Independent
Classifier: Programming Language :: Python
Classifier: Topic :: Software Development :: Libraries :: Python Modules
